MANIFEST.in
setup.cfg
setup.py
CodeStats.egg-info/PKG-INFO
CodeStats.egg-info/SOURCES.txt
CodeStats.egg-info/dependency_links.txt
CodeStats.egg-info/requires.txt
CodeStats.egg-info/top_level.txt
codestats/__init__.py
codestats/api.py
codestats/async_api.py
codestats/bases.py
codestats/levels.py