Metadata-Version: 1.1
Name: CodeStats
Version: 1.1.0
Summary: Wrapper around the Code::Stats API
Home-page: https://www.github.com/niekkeijzer/codestats/
Author: Niek Keijzer
Author-email: info@niekkeijzer.com
License: UNKNOWN
Download-URL: https://github.com/NiekKeijzer/CodeStats/archive/1.1..tar.gz
Platform: UNKNOWN
